colin/__init__.py
colin/__main__.py
colin/exceptions.py
colin/models.py
colin/resources.py
colin/settings.py
colin/api/__init__.py
colin/api/compile.py
colin/api/manifest.py
colin/api/mcp.py
colin/api/project.py
colin/blueprints/mcp-guide/.gitignore
colin/blueprints/mcp-guide/README.md
colin/blueprints/mcp-guide/blueprint.toml
colin/blueprints/mcp-guide/colin.toml
colin/blueprints/mcp-guide/models/SKILL.md
colin/blueprints/mcp-guide/models/_script-generator.md
colin/blueprints/mcp-guide/models/_tool-generator.md
colin/blueprints/mcp-skills-sync/.gitignore
colin/blueprints/mcp-skills-sync/blueprint.toml
colin/blueprints/mcp-skills-sync/colin.toml
colin/blueprints/mcp-skills-sync/models/skills.md
colin/blueprints/quickstart/blueprint.toml
colin/blueprints/quickstart/colin.toml
colin/blueprints/quickstart/models/SKILL.md
colin/blueprints/quickstart/models/tips.md
colin/cli/__init__.py
colin/cli/mcp.py
colin/cli/run.py
colin/cli/skills.py
colin/compiler/__init__.py
colin/compiler/cache.py
colin/compiler/context.py
colin/compiler/engine.py
colin/compiler/graph.py
colin/compiler/jinja_env.py
colin/compiler/namespace.py
colin/compiler/rendered.py
colin/compiler/section_parser.py
colin/compiler/sections.py
colin/compiler/state.py
colin/compiler/extensions/__init__.py
colin/compiler/extensions/defer_block.py
colin/compiler/extensions/file_block.py
colin/compiler/extensions/filters.py
colin/compiler/extensions/item_block.py
colin/compiler/extensions/llm_block.py
colin/compiler/extensions/section_block.py
colin/llm/__init__.py
colin/llm/prompts.py
colin/llm/types.py
colin/llm/prompts/classify.md
colin/llm/prompts/complete.md
colin/llm/prompts/extract.md
colin/output/__init__.py
colin/output/base.py
colin/output/local.py
colin/output/skills.py
colin/plugins/__init__.py
colin/plugins/base.py
colin/plugins/inputs/__init__.py
colin/plugins/outputs/__init__.py
colin/plugins/outputs/markdown.py
colin/providers/__init__.py
colin/providers/base.py
colin/providers/context.py
colin_py-0.1.2.dist-info/METADATA
colin_py-0.1.2.dist-info/WHEEL
colin_py-0.1.2.dist-info/entry_points.txt
colin_py-0.1.2.dist-info/RECORD
