Metadata-Version: 2.4
Name: colin-py
Version: 0.1.2
Summary: A context engine for the AI era
Project-URL: Homepage, https://colin.prefect.io
Project-URL: Repository, https://github.com/PrefectHQ/colin
Project-URL: Documentation, https://colin.prefect.io/docs
Author: Prefect Technologies, Inc.
License-Expression: Apache-2.0
Keywords: agent,ai,context,lineage,llm,mcp,skills
Classifier: Intended Audience :: Developers
Classifier: License :: OSI Approved :: Apache Software License
Classifier: Programming Language :: Python :: 3.10
Classifier: Programming Language :: Python :: 3.11
Classifier: Programming Language :: Python :: 3.12
Classifier: Programming Language :: Python :: 3.13
Classifier: Topic :: Scientific/Engineering :: Artificial Intelligence
Classifier: Typing :: Typed
Requires-Python: >=3.10
Requires-Dist: cryptography>=46.0.3
Requires-Dist: cyclopts>=4.0.0
Requires-Dist: fastmcp<3.0.0b2,>=3.0.0b1
Requires-Dist: httpx>=0.27.0
Requires-Dist: jinja2>=3.1.0
Requires-Dist: pathspec>=1.0.3
Requires-Dist: pydantic-ai>=1.39.0
Requires-Dist: pydantic-settings>=2.0.0
Requires-Dist: pydantic>=2.0.0
Requires-Dist: python-frontmatter>=1.0.0
Requires-Dist: rich>=14.2.0
Requires-Dist: tomli-w>=1.2.0
Requires-Dist: tomli>=2.3.0
